pynintendoparental/__init__.py
pynintendoparental/_version.py
pynintendoparental/api.py
pynintendoparental/application.py
pynintendoparental/authenticator.py
pynintendoparental/const.py
pynintendoparental/device.py
pynintendoparental/enum.py
pynintendoparental/exceptions.py
pynintendoparental/player.py
pynintendoparental/py.typed
pynintendoparental/utils.py
pynintendoparental-2.3.2.dist-info/licenses/LICENSE
pynintendoparental-2.3.2.dist-info/METADATA
pynintendoparental-2.3.2.dist-info/WHEEL
pynintendoparental-2.3.2.dist-info/top_level.txt
pynintendoparental-2.3.2.dist-info/RECORD
