Metadata-Version: 2.4
Name: pynintendoparental
Version: 2.3.2
Summary: A Python module to interact with Nintendo Parental Controls
Home-page: http://github.com/pantherale0/pynintendoparental
Author: pantherale0
License: MIT
Classifier: Programming Language :: Python :: 3
Classifier: License :: OSI Approved :: MIT License
Classifier: Operating System :: OS Independent
Requires-Python: >=3.8, <4
License-File: LICENSE
Requires-Dist: pynintendoauth==1.0.2
Provides-Extra: dev
Requires-Dist: aiofiles<26,>=23; extra == "dev"
Requires-Dist: bandit<1.10,>=1.7; extra == "dev"
Requires-Dist: black<26,>=23; extra == "dev"
Requires-Dist: build<1.4,>=0.10; extra == "dev"
Requires-Dist: Faker<41,>=38; extra == "dev"
Requires-Dist: flake8<8,>=6; extra == "dev"
Requires-Dist: isort<8,>=5; extra == "dev"
Requires-Dist: mypy<1.20,>=1.5; extra == "dev"
Requires-Dist: pytest<10,>=7; extra == "dev"
Requires-Dist: pytest-cov<8,>=4; extra == "dev"
Requires-Dist: pytest-asyncio<2.0,>=0.21; extra == "dev"
Requires-Dist: syrupy<6,>=5; extra == "dev"
Requires-Dist: twine<7,>=4; extra == "dev"
Dynamic: author
Dynamic: classifier
Dynamic: description
Dynamic: description-content-type
Dynamic: home-page
Dynamic: license
Dynamic: license-file
Dynamic: provides-extra
Dynamic: requires-dist
Dynamic: requires-python
Dynamic: summary
